seqrule/__init__.py
seqrule/core.py
seqrule/dsl.py
seqrule/types.py
seqrule/analysis/__init__.py
seqrule/analysis/analyzer.py
seqrule/analysis/base.py
seqrule/analysis/complexity.py
seqrule/analysis/performance.py
seqrule/analysis/property.py
seqrule/analysis/scoring.py
seqrule/generators/__init__.py
seqrule/generators/constrained.py
seqrule/generators/constraints.py
seqrule/generators/core.py
seqrule/generators/lazy.py
seqrule/generators/patterns.py
seqrule/rulesets/__init__.py
seqrule/rulesets/dna.py
seqrule/rulesets/eleusis.py
seqrule/rulesets/general.py
seqrule/rulesets/music.py
seqrule/rulesets/pipeline.py
seqrule/rulesets/tea.py
seqrule-1.0.0b1.post1.dist-info/METADATA
seqrule-1.0.0b1.post1.dist-info/WHEEL
seqrule-1.0.0b1.post1.dist-info/licenses/LICENSE
seqrule-1.0.0b1.post1.dist-info/RECORD
