Metadata-Version: 2.4
Name: seqrule
Version: 1.0.0b1.post1
Summary: A library for defining, generating, and validating rules for sequences of objects
Project-URL: Homepage, https://github.com/neumanns-workshop/seqrule
Project-URL: Repository, https://github.com/neumanns-workshop/seqrule
Project-URL: Documentation, https://seqrule.readthedocs.io
Author-email: Jared Neumann <jared@neumannsworkshop.com>
License: MIT
License-File: LICENSE
Keywords: generation,objects,pattern matching,rules,sequence,validation
Classifier: Development Status :: 4 - Beta
Classifier: Intended Audience :: Developers
Classifier: License :: OSI Approved :: MIT License
Classifier: Programming Language :: Python :: 3
Classifier: Programming Language :: Python :: 3.10
Classifier: Programming Language :: Python :: 3.11
Requires-Python: >=3.10
Provides-Extra: api
Requires-Dist: fastapi>=0.104.0; extra == 'api'
Requires-Dist: pydantic>=2.0.0; extra == 'api'
Requires-Dist: uvicorn>=0.24.0; extra == 'api'
Provides-Extra: dev
Requires-Dist: httpx>=0.26.0; extra == 'dev'
Requires-Dist: mypy>=1.6.0; extra == 'dev'
Requires-Dist: pytest-asyncio>=0.23.0; extra == 'dev'
Requires-Dist: pytest-cov>=4.1.0; extra == 'dev'
Requires-Dist: pytest>=7.4.0; extra == 'dev'
Requires-Dist: ruff>=0.1.6; extra == 'dev'
Provides-Extra: scripts
Requires-Dist: matplotlib>=3.7.0; extra == 'scripts'
Requires-Dist: numpy>=1.24.0; extra == 'scripts'
Requires-Dist: scipy>=1.10.0; extra == 'scripts'
Requires-Dist: seaborn>=0.12.0; extra == 'scripts'
Requires-Dist: tabulate>=0.9.0; extra == 'scripts'
